datamonster_api/__init__.py
datamonster_api/lib/__init__.py
datamonster_api/lib/aggregation.py
datamonster_api/lib/base.py
datamonster_api/lib/client.py
datamonster_api/lib/company.py
datamonster_api/lib/datamonster.py
datamonster_api/lib/datasource.py
datamonster_api/lib/errors.py
datamonster_api-0.0.2.dist-info/LICENSE
datamonster_api-0.0.2.dist-info/METADATA
datamonster_api-0.0.2.dist-info/WHEEL
datamonster_api-0.0.2.dist-info/top_level.txt
datamonster_api-0.0.2.dist-info/RECORD
