Metadata-Version: 2.1
Name: datamonster-api
Version: 0.0.2
Summary: Library for accessing the datamonster rest API
Home-page: https://github.com/adaptivemgmt/datamonster-api
Author: Kevin Thompson
Author-email: kevin@adaptivemgmt.com
License: UNKNOWN
Platform: UNKNOWN
Classifier: Programming Language :: Python :: 2
Classifier: Programming Language :: Python :: 3
Classifier: License :: OSI Approved :: MIT License
Classifier: Operating System :: OS Independent
Requires-Dist: attrs
Requires-Dist: certifi
Requires-Dist: chardet
Requires-Dist: fastavro
Requires-Dist: funcsigs
Requires-Dist: idna
Requires-Dist: more-itertools
Requires-Dist: numpy
Requires-Dist: pandas
Requires-Dist: pathlib2
Requires-Dist: pluggy
Requires-Dist: py
Requires-Dist: pytest
Requires-Dist: pytest-mock
Requires-Dist: python-dateutil
Requires-Dist: pytz
Requires-Dist: requests
Requires-Dist: scandir
Requires-Dist: six
Requires-Dist: urllib3
